dora_ios_lidar/__init__.py
dora_ios_lidar/__main__.py
dora_ios_lidar/main.py
dora_ios_lidar-0.4.1.dist-info/METADATA
dora_ios_lidar-0.4.1.dist-info/WHEEL
dora_ios_lidar-0.4.1.dist-info/entry_points.txt
dora_ios_lidar-0.4.1.dist-info/top_level.txt
dora_ios_lidar-0.4.1.dist-info/RECORD
