Metadata-Version: 2.4
Name: dora-ios-lidar
Version: 0.4.1
Summary: dora-ios-lidar
Author-email: Your Name <email@email.com>
License: MIT
Requires-Python: >=3.8
Requires-Dist: dora-rs>=0.3.9
Requires-Dist: opencv-python>=4.11.0.86
Requires-Dist: record3d>=1.4
Requires-Dist: scipy
